paintlog/__init__.py
paintlog/color_highlight.py
paintlog/logger.py
paintlog/paint.py
paintlogio_py-0.3.6.dist-info/LICENSE
paintlogio_py-0.3.6.dist-info/METADATA
paintlogio_py-0.3.6.dist-info/WHEEL
paintlogio_py-0.3.6.dist-info/top_level.txt
paintlogio_py-0.3.6.dist-info/RECORD
