Metadata-Version: 2.1
Name: paintlogio-py
Version: 0.3.6
Summary: Logging for important Python applications will become more beautiful and functional!
Author-email: Alexeev Bronislav <bro.alexeev@inbox.ru>
Maintainer-email: Alexeev Bronislav <bro.alexeev@inbox.ru>
License: BSD 3-Clause License
Project-URL: Homepage, https://github.com/alexeev-engineer/paintlog
Project-URL: Issues, https://github.com/alexeev-engineer/paintlog/issues
Project-URL: Repository, https://github.com/alexeev-engineer/paintlog
Project-URL: Changelog, https://github.com/alexeev-engineer/paintlog/main/CHANGELOG.md
Keywords: logging,colors,paint,paintlog,log,messageprinter,msgprinter,message_printer,message,icecream,print,printer,debug
Classifier: Programming Language :: Python :: 3
Classifier: Operating System :: OS Independent
Requires-Python: >=3.10
License-File: LICENSE
Requires-Dist: ruff
Requires-Dist: colorama
Requires-Dist: executing
Requires-Dist: six
Requires-Dist: asttokens
Requires-Dist: Pygments
Requires-Dist: logging
